{
  "metals": {
    "aluminum": {
      "properties": ["lightweight", "corrosion-resistant", "conductive"],
      "substitutes": ["titanium", "magnesium", "certain composites"],
      "common_processes": ["extrusion", "casting", "machining"]
    },
    "steel": {
      "properties": ["strong", "durable", "magnetic"],
      "substitutes": ["aluminum alloys", "titanium", "reinforced polymers"],
      "common_processes": ["forging", "machining", "welding"]
    }
  },
  "polymers": {
    "abs": {
      "properties": ["impact-resistant", "thermoformable", "lightweight"],
      "substitutes": ["pla", "petg", "polycarbonate"],
      "common_processes": ["3d printing", "injection molding"]
    }
  }
}