{
  "schema_version": "1.0.0",
  "generated_at": "2026-04-03T01:49:22.237533+00:00",
  "pairs_compared": 0,
  "repos": [
    {
      "id": "repo-001",
      "url": "https://github.com/nasa-jpl/open-source-rover",
      "status": "missing_3L"
    },
    {
      "id": "repo-002",
      "url": "https://gitlab.com/openflexure/openflexure-microscope",
      "status": "missing_3L"
    },
    {
      "id": "repo-003",
      "url": "https://github.com/evanman83/OURS-project",
      "status": "missing_3L"
    },
    {
      "id": "repo-004",
      "url": "https://github.com/FourThievesVinegar/solderless-microlab",
      "status": "missing_3L"
    },
    {
      "id": "repo-005",
      "url": "https://github.com/openmv/openmv",
      "status": "missing_3L"
    },
    {
      "id": "repo-006",
      "url": "https://github.com/biomurph/Mouse",
      "status": "missing_3L"
    },
    {
      "id": "repo-007",
      "url": "https://github.com/tjko/fanpico",
      "status": "missing_3L"
    },
    {
      "id": "repo-008",
      "url": "https://github.com/beagleboard/beaglebone-black",
      "status": "missing_3L"
    },
    {
      "id": "repo-009",
      "url": "https://github.com/prusa3d/Original-Prusa-i3",
      "status": "missing_3L"
    },
    {
      "id": "repo-010",
      "url": "https://github.com/sparkfun/RedBoard",
      "status": "missing_3L"
    },
    {
      "id": "repo-011",
      "url": "https://github.com/cnlohr/ch32v003fun",
      "status": "missing_3L"
    },
    {
      "id": "repo-012",
      "url": "https://github.com/keebio/iris-case",
      "status": "missing_3L"
    },
    {
      "id": "bha-centrifuge",
      "url": "https://gitlab.waag.org/biohack/BHA_Centrifuge",
      "status": "missing_3L"
    },
    {
      "id": "bha-bioreactor",
      "url": "https://gitlab.waag.org/biohack/BHA_Bioreactor",
      "status": "missing_3L"
    },
    {
      "id": "bha-gelbox",
      "url": "https://gitlab.waag.org/biohack/BHA_GelBox",
      "status": "missing_3L"
    },
    {
      "id": "bha-incubator",
      "url": "https://gitlab.waag.org/biohack/BHA_Incubator",
      "status": "missing_3L"
    },
    {
      "id": "bha-microscope",
      "url": "https://gitlab.waag.org/biohack/BHA_Microscope",
      "status": "missing_3L"
    },
    {
      "id": "bha-peristaltic-pump",
      "url": "https://gitlab.waag.org/biohack/BHA_PeristalticPump",
      "status": "missing_3L"
    },
    {
      "id": "bha-photobioreactor",
      "url": "https://gitlab.waag.org/biohack/BHA_Photobioreactor",
      "status": "missing_3L"
    },
    {
      "id": "bha-stirrer",
      "url": "https://gitlab.waag.org/biohack/BHA_Stirrer",
      "status": "missing_3L"
    },
    {
      "id": "bha-spectrophotometer",
      "url": "https://gitlab.waag.org/biohack/BHA_Spectrophotometer",
      "status": "missing_3L"
    },
    {
      "id": "bha-syringe-pump",
      "url": "https://gitlab.waag.org/biohack/BHA_SyringePump",
      "status": "missing_3L"
    },
    {
      "id": "bha-thermocycler",
      "url": "https://gitlab.waag.org/biohack/BHA_Thermocycler",
      "status": "missing_3L"
    },
    {
      "id": "bha-webcam-microscope",
      "url": "https://gitlab.waag.org/biohack/BHA_Webcam_Microscope",
      "status": "missing_3L"
    },
    {
      "id": "bha-biohackboard",
      "url": "https://gitlab.waag.org/biohack/BioHackBoard",
      "status": "missing_3L"
    },
    {
      "id": "air-quality-sensor-nrf52840-v2-ed3",
      "url": "https://github.com/smartboxchannel/eON-AQSENS_213_V2_ED3-EFEKTALAB",
      "status": "missing_3L"
    }
  ]
}
